ww_time_mcp/__init__.py
ww_time_mcp/server.py
ww_time_mcp-0.1.0.dist-info/METADATA
ww_time_mcp-0.1.0.dist-info/WHEEL
ww_time_mcp-0.1.0.dist-info/entry_points.txt
ww_time_mcp-0.1.0.dist-info/top_level.txt
ww_time_mcp-0.1.0.dist-info/RECORD
